hs_m3u8/__init__.py
hs_m3u8/main.py
hs_m3u8-0.1.8.dist-info/METADATA
hs_m3u8-0.1.8.dist-info/WHEEL
hs_m3u8-0.1.8.dist-info/RECORD
