Metadata-Version: 2.4
Name: hs-m3u8
Version: 0.1.8
Summary: m3u8 下载器
Project-URL: homepage, https://github.com/x-haose/hs-m3u8
Project-URL: repository, https://github.com/x-haose/hs-m3u8
Project-URL: documentation, https://github.com/x-haose/hs-m3u8
Author-email: 昊色居士 <xhrtxh@gmail.com>
License-Expression: MIT
Classifier: Development Status :: 4 - Beta
Classifier: Intended Audience :: Developers
Classifier: License :: OSI Approved :: MIT License
Classifier: Operating System :: MacOS :: MacOS X
Classifier: Operating System :: Microsoft :: Windows
Classifier: Operating System :: POSIX :: BSD
Classifier: Operating System :: POSIX :: Linux
Classifier: Programming Language :: Python :: 3.10
Classifier: Programming Language :: Python :: 3.11
Classifier: Programming Language :: Python :: 3.12
Classifier: Programming Language :: Python :: 3.13
Classifier: Topic :: Software Development :: Libraries :: Python Modules
Requires-Python: >=3.10
Requires-Dist: hssp>=0.4.18
Requires-Dist: m3u8>=6.0.0
